LICENSE
MANIFEST.in
README.md
setup.py
critical/__init__.py
critical/conf.py
critical/core.py
critical/middleware.py
critical/models.py
critical/parser.py
critical/util.py
critical/templates/critical/async_snippet.html
critical/templatetags/__init__.py
critical/templatetags/critical.py
django_critical.egg-info/PKG-INFO
django_critical.egg-info/SOURCES.txt
django_critical.egg-info/dependency_links.txt
django_critical.egg-info/not-zip-safe
django_critical.egg-info/requires.txt
django_critical.egg-info/top_level.txt