Metadata-Version: 1.1
Name: django-critical
Version: 0.1
Summary: Inlines critical path CSS and defers loading full CSS asynchronously.
Home-page: https://github.com/martinblech/django-critical
Author: Martin Blech
Author-email: martinblech@gmail.com
License: UNKNOWN
Platform: UNKNOWN
Classifier: Development Status :: 4 - Beta
Classifier: Environment :: Web Environment
Classifier: Framework :: Django
Classifier: Intended Audience :: Developers
Classifier: License :: OSI Approved :: MIT License
Classifier: Operating System :: OS Independent
Classifier: Programming Language :: Python
Classifier: Programming Language :: Python :: 2
Classifier: Programming Language :: Python :: 3
Classifier: Topic :: Internet :: WWW/HTTP
